pydosLinux/ASCII.py
pydosLinux/BootLoader.py
pydosLinux/Calcutator.py
pydosLinux/Help.py
pydosLinux/MusicDownload.py
pydosLinux/Notepad.py
pydosLinux/PPkg.py
pydosLinux/PyMusic.py
pydosLinux/PyRename.py
pydosLinux/__init__.py
pydosLinux/kernel.py
pydosLinux/sysver.py
pydosLinux-0.2.8066.dist-info/LICENSE
pydosLinux-0.2.8066.dist-info/METADATA
pydosLinux-0.2.8066.dist-info/WHEEL
pydosLinux-0.2.8066.dist-info/top_level.txt
pydosLinux-0.2.8066.dist-info/RECORD
