Metadata-Version: 2.1
Name: pydosLinux
Version: 0.2.8066
Summary: py-dos is a toolset.
Home-page: https://gitee.com/yizhigezi_yijiafeiji/py-dos
Author: yijiafeiji
Author-email: jjy1207826398@163.com
License: UNKNOWN
Project-URL: Bug Tracker, https://gitee.com/yizhigezi_yijiafeiji/py-dos/issues
Platform: UNKNOWN
Classifier: Programming Language :: Python :: 3
Classifier: License :: OSI Approved :: MIT License
Classifier: Operating System :: Unix
Requires-Python: >=3.6
License-File: LICENSE
